[
    {
        "id": 0,
        "daynight": "d",
        "color": "N",
        "production": "brg",
        "prerequisite": null,
        "reward": null,
        "imgsrc": null,
        "set": "pfb"
    },
    {
        "id": 1,
        "daynight": "d",
        "color": "R",
        "production": "br",
        "prerequisite": null,
        "reward": null,
        "imgsrc": null,
        "set": "base"
    },
    {
        "id": 2,
        "daynight": "d",
        "color": "B",
        "production": "bb",
        "prerequisite": null,
        "reward": null,
        "imgsrc": null,
        "set": "base"
    },
    {
        "id": 3,
        "daynight": "d",
        "color": "G",
        "production": null,
        "prerequisite": null,
        "reward": "4",
        "imgsrc": null,
        "set": "base"
    },
    {
        "id": 4,
        "daynight": "d",
        "color": "R",
        "production": "bg",
        "prerequisite": null,
        "reward": null,
        "imgsrc": null,
        "set": "base"
    },
    {
        "id": 5,
        "daynight": "d",
        "color": "G",
        "production": "r",
        "prerequisite": null,
        "reward": "2",
        "imgsrc": null,
        "set": "base"
    },
    {
        "id": 6,
        "daynight": "d",
        "color": "B",
        "production": "cb",
        "prerequisite": null,
        "reward": null,
        "imgsrc": null,
        "set": "base"
    },
    {
        "id": 7,
        "daynight": "d",
        "color": "R",
        "production": "rg",
        "prerequisite": null,
        "reward": null,
        "imgsrc": null,
        "set": "base"
    },
    {
        "id": 8,
        "daynight": "d",
        "color": "G",
        "production": "cr",
        "prerequisite": null,
        "reward": null,
        "imgsrc": null,
        "set": "base"
    },
    {
        "id": 9,
        "daynight": "d",
        "color": "B",
        "production": null,
        "prerequisite": null,
        "reward": "5",
        "imgsrc": null,
        "set": "base"
    },
    {
        "id": 10,
        "daynight": "d",
        "color": "R",
        "production": null,
        "prerequisite": null,
        "reward": "2*n",
        "imgsrc": null,
        "set": "base"
    },
    {
        "id": 11,
        "daynight": "d",
        "color": "G",
        "production": null,
        "prerequisite": null,
        "reward": "2*c",
        "imgsrc": null,
        "set": "base"
    },
    {
        "id": 12,
        "daynight": "d",
        "color": "Y",
        "production": "cg",
        "prerequisite": null,
        "reward": null,
        "imgsrc": null,
        "set": "base"
    },
    {
        "id": 13,
        "daynight": "d",
        "color": "B",
        "production": null,
        "prerequisite": null,
        "reward": "2*b",
        "imgsrc": null,
        "set": "base"
    },
    {
        "id": 14,
        "daynight": "d",
        "color": "R",
        "production": "g",
        "prerequisite": null,
        "reward": "2*n",
        "imgsrc": null,
        "set": "base"
    },
    {
        "id": 15,
        "daynight": "d",
        "color": "G",
        "production": "c",
        "prerequisite": null,
        "reward": "2*r",
        "imgsrc": null,
        "set": "base"
    },
    {
        "id": 16,
        "daynight": "d",
        "color": "R",
        "production": "r",
        "prerequisite": null,
        "reward": "2*r",
        "imgsrc": null,
        "set": "base"
    },
    {
        "id": 17,
        "daynight": "d",
        "color": "B",
        "production": "b",
        "prerequisite": "rr",
        "reward": "3*b",
        "imgsrc": null,
        "set": "base"
    },
    {
        "id": 18,
        "daynight": "d",
        "color": "G",
        "production": "r",
        "prerequisite": null,
        "reward": "10*s",
        "imgsrc": null,
        "set": "base"
    },
    {
        "id": 19,
        "daynight": "d",
        "color": "R",
        "production": "g",
        "prerequisite": null,
        "reward": "2*g",
        "imgsrc": null,
        "set": "base"
    },
    {
        "id": 20,
        "daynight": "n",
        "color": "G",
        "production": "c",
        "prerequisite": "b",
        "reward": "2*n",
        "imgsrc": null,
        "set": "base"
    },
    {
        "id": 21,
        "daynight": "n",
        "color": "B",
        "production": null,
        "prerequisite": "bb",
        "reward": "8",
        "imgsrc": null,
        "set": "base"
    },
    {
        "id": 22,
        "daynight": "n",
        "color": "G",
        "production": "c",
        "prerequisite": null,
        "reward": "1*c",
        "imgsrc": null,
        "set": "base"
    },
    {
        "id": 23,
        "daynight": "n",
        "color": "R",
        "production": "br",
        "prerequisite": null,
        "reward": "10*s",
        "imgsrc": null,
        "set": "base"
    },
    {
        "id": 24,
        "daynight": "n",
        "color": "B",
        "production": "b",
        "prerequisite": "r",
        "reward": "2*n",
        "imgsrc": null,
        "set": "base"
    },
    {
        "id": 25,
        "daynight": "n",
        "color": "Y",
        "production": null,
        "prerequisite": null,
        "reward": "2*(Y+G)",
        "imgsrc": null,
        "set": "base"
    },
    {
        "id": 26,
        "daynight": "n",
        "color": "R",
        "production": "r",
        "prerequisite": null,
        "reward": "3*g",
        "imgsrc": null,
        "set": "base"
    },
    {
        "id": 27,
        "daynight": "n",
        "color": "Y",
        "production": null,
        "prerequisite": null,
        "reward": "1*(Y+B)",
        "imgsrc": null,
        "set": "base"
    },
    {
        "id": 28,
        "daynight": "n",
        "color": "R",
        "production": "b",
        "prerequisite": null,
        "reward": "3*r",
        "imgsrc": null,
        "set": "base"
    },
    {
        "id": 29,
        "daynight": "n",
        "color": "Y",
        "production": "g",
        "prerequisite": null,
        "reward": "2*g",
        "imgsrc": null,
        "set": "base"
    },
    {
        "id": 30,
        "daynight": "n",
        "color": "R",
        "production": "b",
        "prerequisite": null,
        "reward": "2*b",
        "imgsrc": null,
        "set": "base"
    },
    {
        "id": 31,
        "daynight": "n",
        "color": "Y",
        "production": null,
        "prerequisite": null,
        "reward": "1*(Y+R)",
        "imgsrc": null,
        "set": "base"
    },
    {
        "id": 32,
        "daynight": "n",
        "color": "R",
        "production": "br",
        "prerequisite": "bbb",
        "reward": "7",
        "imgsrc": null,
        "set": "base"
    },
    {
        "id": 33,
        "daynight": "n",
        "color": "Y",
        "production": null,
        "prerequisite": null,
        "reward": "3*g",
        "imgsrc": null,
        "set": "base"
    },
    {
        "id": 34,
        "daynight": "n",
        "color": "G",
        "production": "r",
        "prerequisite": "bb",
        "reward": "3*r",
        "imgsrc": null,
        "set": "base"
    },
    {
        "id": 35,
        "daynight": "n",
        "color": "Y",
        "production": "r",
        "prerequisite": null,
        "reward": "1*s",
        "imgsrc": null,
        "set": "base"
    },
    {
        "id": 36,
        "daynight": "n",
        "color": "R",
        "production": null,
        "prerequisite": "rr",
        "reward": "4*g",
        "imgsrc": null,
        "set": "base"
    },
    {
        "id": 37,
        "daynight": "n",
        "color": "Y",
        "production": null,
        "prerequisite": "g",
        "reward": "3*n",
        "imgsrc": null,
        "set": "base"
    },
    {
        "id": 38,
        "daynight": "n",
        "color": "G",
        "production": "b",
        "prerequisite": "rg",
        "reward": "3*c",
        "imgsrc": null,
        "set": "base"
    },
    {
        "id": 39,
        "daynight": "n",
        "color": "R",
        "production": "bg",
        "prerequisite": "rr",
        "reward": "9",
        "imgsrc": null,
        "set": "base"
    },
    {
        "id": 40,
        "daynight": "n",
        "color": "B",
        "production": null,
        "prerequisite": "brg",
        "reward": "3*n",
        "imgsrc": null,
        "set": "base"
    },
    {
        "id": 41,
        "daynight": "d",
        "color": "G",
        "production": "g",
        "prerequisite": "bbr",
        "reward": "4*n",
        "imgsrc": null,
        "set": "base"
    },
    {
        "id": 42,
        "daynight": "d",
        "color": "Y",
        "production": null,
        "prerequisite": "br",
        "reward": "2*(Y+G)",
        "imgsrc": null,
        "set": "base"
    },
    {
        "id": 43,
        "daynight": "d",
        "color": "B",
        "production": "b",
        "prerequisite": null,
        "reward": "10*s",
        "imgsrc": null,
        "set": "base"
    },
    {
        "id": 44,
        "daynight": "d",
        "color": "Y",
        "production": null,
        "prerequisite": "bg",
        "reward": "2*(Y+B)",
        "imgsrc": null,
        "set": "base"
    },
    {
        "id": 45,
        "daynight": "d",
        "color": "G",
        "production": "b",
        "prerequisite": "rrr",
        "reward": "13",
        "imgsrc": null,
        "set": "base"
    },
    {
        "id": 46,
        "daynight": "d",
        "color": "B",
        "production": "c",
        "prerequisite": "bbr",
        "reward": "10",
        "imgsrc": null,
        "set": "base"
    },
    {
        "id": 47,
        "daynight": "d",
        "color": "Y",
        "production": null,
        "prerequisite": "rg",
        "reward": "2*(Y+R)",
        "imgsrc": null,
        "set": "base"
    },
    {
        "id": 48,
        "daynight": "d",
        "color": "R",
        "production": "r",
        "prerequisite": null,
        "reward": "3*b",
        "imgsrc": null,
        "set": "base"
    },
    {
        "id": 49,
        "daynight": "d",
        "color": "B",
        "production": "c",
        "prerequisite": "bbg",
        "reward": "12",
        "imgsrc": null,
        "set": "base"
    },
    {
        "id": 50,
        "daynight": "d",
        "color": "Y",
        "production": "b",
        "prerequisite": "gg",
        "reward": "4*G",
        "imgsrc": null,
        "set": "base"
    },
    {
        "id": 51,
        "daynight": "d",
        "color": "B",
        "production": "b",
        "prerequisite": "bbbb",
        "reward": "14",
        "imgsrc": null,
        "set": "base"
    },
    {
        "id": 52,
        "daynight": "d",
        "color": "R",
        "production": null,
        "prerequisite": "bbb",
        "reward": "4*r",
        "imgsrc": null,
        "set": "base"
    },
    {
        "id": 53,
        "daynight": "d",
        "color": "Y",
        "production": "r",
        "prerequisite": "gg",
        "reward": "4*R",
        "imgsrc": null,
        "set": "base"
    },
    {
        "id": 54,
        "daynight": "d",
        "color": "G",
        "production": "r",
        "prerequisite": "gg",
        "reward": "4*c",
        "imgsrc": null,
        "set": "base"
    },
    {
        "id": 55,
        "daynight": "d",
        "color": "B",
        "production": "bc",
        "prerequisite": "rgg",
        "reward": "3*b",
        "imgsrc": null,
        "set": "base"
    },
    {
        "id": 56,
        "daynight": "d",
        "color": "Y",
        "production": "g",
        "prerequisite": "brr",
        "reward": "4*B",
        "imgsrc": null,
        "set": "base"
    },
    {
        "id": 57,
        "daynight": "d",
        "color": "R",
        "production": null,
        "prerequisite": "ggg",
        "reward": "4*b",
        "imgsrc": null,
        "set": "base"
    },
    {
        "id": 58,
        "daynight": "d",
        "color": "G",
        "production": "c",
        "prerequisite": "rrr",
        "reward": "3*c",
        "imgsrc": null,
        "set": "base"
    },
    {
        "id": 59,
        "daynight": "d",
        "color": "Y",
        "production": "c",
        "prerequisite": "brrr",
        "reward": "3*(Y+R)",
        "imgsrc": null,
        "set": "base"
    },
    {
        "id": 60,
        "daynight": "d",
        "color": "B",
        "production": "c",
        "prerequisite": "bbrr",
        "reward": "16",
        "imgsrc": null,
        "set": "base"
    },
    {
        "id": 61,
        "daynight": "d",
        "color": "G",
        "production": "g",
        "prerequisite": "rrrr",
        "reward": "17",
        "imgsrc": null,
        "set": "base"
    },
    {
        "id": 62,
        "daynight": "d",
        "color": "Y",
        "production": "c",
        "prerequisite": "ggg",
        "reward": "3*(Y+B)",
        "imgsrc": null,
        "set": "base"
    },
    {
        "id": 63,
        "daynight": "d",
        "color": "G",
        "production": "c",
        "prerequisite": "rrg",
        "reward": "15",
        "imgsrc": null,
        "set": "base"
    },
    {
        "id": 64,
        "daynight": "d",
        "color": "B",
        "production": "c",
        "prerequisite": "bbgg",
        "reward": "18",
        "imgsrc": null,
        "set": "base"
    },
    {
        "id": 65,
        "daynight": "d",
        "color": "Y",
        "production": "c",
        "prerequisite": "ggg",
        "reward": "3*(Y+G)",
        "imgsrc": null,
        "set": "base"
    },
    {
        "id": 66,
        "daynight": "d",
        "color": "B",
        "production": null,
        "prerequisite": "bbbb",
        "reward": "20",
        "imgsrc": null,
        "set": "base"
    },
    {
        "id": 67,
        "daynight": "d",
        "color": "G",
        "production": "c",
        "prerequisite": "rrgg",
        "reward": "19",
        "imgsrc": null,
        "set": "base"
    },
    {
        "id": 68,
        "daynight": "d",
        "color": "B",
        "production": null,
        "prerequisite": "bbbbb",
        "reward": "24",
        "imgsrc": null,
        "set": "base"
    },
    {
        "id": 69,
        "daynight": "d",
        "color": "R",
        "production": "c",
        "prerequisite": null,
        "reward": "7*i",
        "imgsrc": null,
        "set": "pfb"
    },
    {
        "id": 70,
        "daynight": "d",
        "color": "N",
        "production": "c",
        "prerequisite": null,
        "reward": "6",
        "imgsrc": null,
        "set": "pfb"
    },
    {
        "id": 71,
        "daynight": "n",
        "color": "G",
        "production": "b",
        "prerequisite": null,
        "reward": "7*i",
        "imgsrc": null,
        "set": "pfb"
    },
    {
        "id": 72,
        "daynight": "n",
        "color": "N",
        "production": null,
        "prerequisite": "rrrrr",
        "reward": "26",
        "imgsrc": null,
        "set": "pfb"
    },
    {
        "id": 73,
        "daynight": "n",
        "color": "Y",
        "production": "r",
        "prerequisite": "gggg",
        "reward": "5*N",
        "imgsrc": null,
        "set": "pfb"
    },
    {
        "id": 74,
        "daynight": "n",
        "color": "N",
        "production": "g",
        "prerequisite": null,
        "reward": "7*i",
        "imgsrc": null,
        "set": "pfb"
    },
    {
        "id": 75,
        "daynight": "n",
        "color": "B",
        "production": "c",
        "prerequisite": "bbbbbb",
        "reward": "28",
        "imgsrc": null,
        "set": "pfb"
    },
    {
        "id": 76,
        "daynight": "n",
        "color": "N",
        "production": null,
        "prerequisite": "bbrrgg",
        "reward": "4*N",
        "imgsrc": null,
        "set": "pfb"
    }
]